AUTHORS.rst
CONTRIBUTING.rst
HISTORY.rst
LICENSE
MANIFEST.in
README.md
setup.cfg
setup.py
docs/Makefile
docs/authors.rst
docs/conf.py
docs/contributing.rst
docs/history.rst
docs/index.rst
docs/installation.rst
docs/make.bat
docs/readme.rst
docs/usage.rst
pyGRBaglow/__init__.py
pyGRBaglow/cli.py
pyGRBaglow/constants.py
pyGRBaglow/igm.py
pyGRBaglow/reddening.py
pyGRBaglow/synchrotron_model.c
pyGRBaglow/synchrotron_model.pyx
pyGRBaglow/template_models.py
pyGRBaglow.egg-info/PKG-INFO
pyGRBaglow.egg-info/SOURCES.txt
pyGRBaglow.egg-info/dependency_links.txt
pyGRBaglow.egg-info/entry_points.txt
pyGRBaglow.egg-info/not-zip-safe
pyGRBaglow.egg-info/requires.txt
pyGRBaglow.egg-info/top_level.txt
tests/lc_test.dat
tests/test_pyGRBaglow.py
tests/data/lc_synchrotron.dat
tests/data/lc_synchrotron_windy.dat
tests/data/test_dla_05_1e15.dat
tests/data/test_dla_15_1e15.dat
tests/data/test_dla_15_1e20.dat
tests/data/test_dla_5_1e15.dat
tests/data/test_dla_5_1e20.dat
tests/data/test_gas_abs_02.dat
tests/data/test_gas_abs_1.dat
tests/data/test_igm_madau_05.dat
tests/data/test_igm_madau_10.dat
tests/data/test_igm_madau_2.dat
tests/data/test_igm_meiksin_05.dat
tests/data/test_igm_meiksin_10.dat
tests/data/test_igm_meiksin_2.dat
tests/data/test_lc_BPL.dat
tests/data/test_lc_SPL.dat
tests/data/test_reddening_Li_calzetti.dat
tests/data/test_reddening_Li_grb1.dat
tests/data/test_reddening_Li_grb2.dat
tests/data/test_reddening_Li_linear.dat
tests/data/test_reddening_Li_lmc.dat
tests/data/test_reddening_Li_mw.dat
tests/data/test_reddening_Li_smc.dat
tests/data/test_reddening_Pei_lmc.dat
tests/data/test_reddening_Pei_mw.dat
tests/data/test_reddening_Pei_smc.dat