Metadata-Version: 2.1
Name: pyGRBaglow
Version: 0.1.3
Summary: GRB afterglow modelling with standard synchrotronmodel of Granot & Sari 2002
Home-page: https://github.com/dcorre/pyGRBaglow
Author: David Corre
Author-email: david.corre.fr@gmail.com
License: MIT license
Download-URL: https://github.com/dcorre/pyGRBaglow/archive/v0.1.3.tar.gz
Keywords: GRB,afterglow,fireball,synchrotron,light curve
Platform: UNKNOWN
Classifier: Development Status :: 4 - Beta
Classifier: Topic :: Scientific/Engineering :: Astronomy
Classifier: Intended Audience :: Science/Research
Classifier: License :: OSI Approved :: MIT License
Classifier: Natural Language :: English
Classifier: Programming Language :: Python :: 3
Classifier: Programming Language :: Python :: 3.5
Classifier: Programming Language :: Python :: 3.6
Classifier: Programming Language :: Python :: 3.7
Classifier: Programming Language :: Python :: 3.8
